README.rst
setup.cfg
setup.py
touchworks/__init__.py
touchworks/logger.py
touchworks.egg-info/PKG-INFO
touchworks.egg-info/SOURCES.txt
touchworks.egg-info/dependency_links.txt
touchworks.egg-info/not-zip-safe
touchworks.egg-info/requires.txt
touchworks.egg-info/top_level.txt