Metadata-Version: 1.1
Name: touchworks
Version: 0.2
Summary: Allscripts Touchworks API Client for Python
Home-page: https://github.com/farshidce/touchworks-python
Author: Farshid Ghods
Author-email: farshid.ghods@gmail.com
License: MIT
Download-URL: https://github.com/farshidce/touchworks-python/tarball/0.2
Keywords: health,api,touchworks,ehr
Platform: any
Classifier: Development Status :: 5 - Production/Stable
Classifier: Environment :: Web Environment
Classifier: Intended Audience :: Developers
Classifier: Intended Audience :: Healthcare Industry
Classifier: License :: OSI Approved :: MIT License
Classifier: Operating System :: OS Independent
Classifier: Programming Language :: Python
Classifier: Programming Language :: Python :: 2.7
Classifier: Programming Language :: Python :: 3.4
Classifier: Programming Language :: Python :: Implementation :: PyPy
Classifier: Topic :: Internet :: WWW/HTTP :: Dynamic Content
Classifier: Topic :: Software Development :: Libraries :: Python Modules
